intimezone/Error.py
intimezone/UTC.py
intimezone/__about__.py
intimezone/__init__.py
intimezone/convert.py
intimezone-1.0.2.dist-info/METADATA
intimezone-1.0.2.dist-info/RECORD
intimezone-1.0.2.dist-info/WHEEL
intimezone-1.0.2.dist-info/top_level.txt
